npcompare/__init__.py
npcompare/compare.py
npcompare/estimate.py
npcompare/estimatebfs.py
npcompare/estimatelindleybfs.py
npcompare/fourierseries.py
npcompare/models/estimatebfs_mixture.stan
npcompare/models/estimatebfs_single.stan
npcompare/models/estimatelindleybfs_mixture.stan
npcompare/models/estimatelindleybfs_single.stan
npcompare-0.13.1.dist-info/DESCRIPTION.rst
npcompare-0.13.1.dist-info/METADATA
npcompare-0.13.1.dist-info/RECORD
npcompare-0.13.1.dist-info/WHEEL
npcompare-0.13.1.dist-info/metadata.json
npcompare-0.13.1.dist-info/top_level.txt
