Metadata-Version: 2.0
Name: npcompare
Version: 0.13.1
Summary: Nonparametric methods for density estimation and comparison
Home-page: http://npcompare.marcoinacio.com/
Author: Marco Inacio
Author-email: pythonpackages@marcoinacio.com
License: GPL3
Keywords: nonparametric,density comparision,density estimation
Platform: UNKNOWN
Requires-Dist: numpy
Requires-Dist: scipy
